__init__.py
main.py
Typesquatting_threat5-1.0.0.dist-info/LICENSE
Typesquatting_threat5-1.0.0.dist-info/METADATA
Typesquatting_threat5-1.0.0.dist-info/WHEEL
Typesquatting_threat5-1.0.0.dist-info/top_level.txt
Typesquatting_threat5-1.0.0.dist-info/RECORD
